nx584mqtt/api.py
nx584mqtt/api_alt.py
nx584mqtt/client.py
nx584mqtt/controller.py
nx584mqtt/event_queue.py
nx584mqtt/mail.py
nx584mqtt/main.py
nx584mqtt/model.py
nx584mqtt/mqtt_client.py
nx584mqtt-0.1.13.data/scripts/nx584_client
nx584mqtt-0.1.13.data/scripts/nx584_server
nx584mqtt-0.1.13.dist-info/LICENSE
nx584mqtt-0.1.13.dist-info/METADATA
nx584mqtt-0.1.13.dist-info/WHEEL
nx584mqtt-0.1.13.dist-info/top_level.txt
nx584mqtt-0.1.13.dist-info/RECORD
