Metadata-Version: 2.1
Name: nx584mqtt
Version: 0.1.13
Summary: NX584/NX8E Interface Library and Server with MQTT client
Home-page: http://github.com/rocket4321/nx584mqtt
Author: rocket4321
License: UNKNOWN
Platform: UNKNOWN
Requires-Dist: paho-mqtt
Requires-Dist: requests
Requires-Dist: pyserial
Provides-Extra: client
Requires-Dist: prettytable ; extra == 'client'
Provides-Extra: full
Requires-Dist: flask ; extra == 'full'
Requires-Dist: prettytable ; extra == 'full'
Provides-Extra: http
Requires-Dist: flask ; extra == 'http'
